bx24_orm/__init__.py
bx24_orm/core/__init__.py
bx24_orm/core/adapter.py
bx24_orm/core/bases.py
bx24_orm/core/bx_interface.py
bx24_orm/core/fields.py
bx24_orm/core/repository.py
bx24_orm/core/settings.py
bx24_orm/core/token_storage.py
bx24_orm/core/utils.py
bx24_orm/core/exceptions/__init__.py
bx24_orm/core/exceptions/bx_exceptions.py
bx24_orm/core/exceptions/code_exceptions.py
bx24_orm/enitiy/__init__.py
bx24_orm/enitiy/base.py
bx24_orm/enitiy/crm.py
bx24_orm/scripts/__init__.py
bx24_orm/scripts/command_line.py
bx24_orm/test/__init__.py
bx24_orm/test/tests.py
bx24_orm-0.0.3.dist-info/LICENSE
bx24_orm-0.0.3.dist-info/METADATA
bx24_orm-0.0.3.dist-info/WHEEL
bx24_orm-0.0.3.dist-info/entry_points.txt
bx24_orm-0.0.3.dist-info/top_level.txt
bx24_orm-0.0.3.dist-info/RECORD
