Metadata-Version: 2.1
Name: bx24-orm
Version: 0.0.3
Summary: Easy to use Django-styled API wrapper for Bitrix 24
Home-page: https://github.com/dmitriilazukov/bx24_orm
Author: Dmitrii Lazukov
Author-email: dmitriilazukov@gmail.com
License: MIT
Platform: UNKNOWN
Classifier: Programming Language :: Python :: 2.7
Classifier: Programming Language :: Python :: 3
Classifier: License :: OSI Approved :: MIT License
Classifier: Operating System :: OS Independent
Requires-Dist: requests
Requires-Dist: six
Requires-Dist: python-dateutil
